{"status":"pass","mode":"test","identity":{"runId":"6800572b-99b0-470f-83f9-537c1312c175","seed":7121367326633033663,"reportPath":".fozzy/runs/6800572b-99b0-470f-83f9-537c1312c175/report.json","artifactsDir":".fozzy/runs/6800572b-99b0-470f-83f9-537c1312c175"},"startedAt":"2026-03-24T12:05:33.068075Z","finishedAt":"2026-03-24T12:05:33.077405Z","durationMs":9,"durationNs":8369875,"tests":{"passed":1,"failed":0,"skipped":0},"memory":{"allocCount":0,"freeCount":0,"failedAllocCount":0,"inUseBytes":0,"peakBytes":0,"leakedBytes":0,"leakedAllocs":0}}